CHANGES.rst
CONTRIBUTORS.rst
LICENSE.txt
MANIFEST.in
README.rst
requirements.txt
setup.py
docs/Makefile
docs/__init__.py
docs/conf.py
docs/index.rst
docs/make.bat
docs/api/models.epublication.rst
docs/api/models.libraries.rst
docs/api/models.riv.rst
docs/api/models.rst
docs/api/modules.rst
docs/resources/new-epublication-request.py
src/edeposit/__init__.py
src/edeposit.amqp.models.egg-info/PKG-INFO
src/edeposit.amqp.models.egg-info/SOURCES.txt
src/edeposit.amqp.models.egg-info/dependency_links.txt
src/edeposit.amqp.models.egg-info/requires.txt
src/edeposit.amqp.models.egg-info/top_level.txt
src/edeposit.amqp.models.egg-info/zip-safe
tests/test_edeposit.amqp.models.py