Metadata-Version: 1.1
Name: edeposit.amqp.models
Version: 0.2.3
Summary: Input structures for the eDeposit website and amqp communication.
Home-page: https://github.com/edeposit/edeposit.amqp.models
Author: Jan Stavěl
Author-email: stavel.jan@gmail.com
License: MIT
Platform: UNKNOWN
Classifier: Intended Audience :: Developers
Classifier: Programming Language :: Python :: 2
Classifier: Programming Language :: Python :: 2.7
Classifier: License :: OSI Approved :: MIT License
